kaldiio/__init__.py
kaldiio/compression_header.py
kaldiio/highlevel.py
kaldiio/matio.py
kaldiio/python_wave.py
kaldiio/utils.py
kaldiio/wavio.py
kaldiio-2.18.0.dist-info/LICENSE
kaldiio-2.18.0.dist-info/METADATA
kaldiio-2.18.0.dist-info/WHEEL
kaldiio-2.18.0.dist-info/top_level.txt
kaldiio-2.18.0.dist-info/RECORD
