Metadata-Version: 2.1
Name: kaldiio
Version: 2.18.0
Summary: Kaldi-ark loading and writing module
Home-page: https://github.com/nttcslab-sp/kaldiio
Author: nttcslab-sp
Classifier: Development Status :: 5 - Production/Stable
Classifier: Intended Audience :: Science/Research
Classifier: Programming Language :: Python :: 2.7
Classifier: Programming Language :: Python :: 3.5
Classifier: Programming Language :: Python :: 3.6
Classifier: Programming Language :: Python :: 3.7
Classifier: Programming Language :: Python :: 3.8
Classifier: Programming Language :: Python :: 3.9
Classifier: Programming Language :: Python :: 3.10
Classifier: Topic :: Multimedia :: Sound/Audio :: Analysis
License-File: LICENSE
Requires-Dist: numpy
